CHANGES.rst
DESCRIPTION.rst
MANIFEST.in
README.md
setup.py
src/rnb2docker/__init__.py
src/rnb2docker/generator.py
src/rnb2docker.egg-info/PKG-INFO
src/rnb2docker.egg-info/SOURCES.txt
src/rnb2docker.egg-info/dependency_links.txt
src/rnb2docker.egg-info/entry_points.txt
src/rnb2docker.egg-info/top_level.txt