Metadata-Version: 1.1
Name: rnb2docker
Version: 0.0.1
Summary: Library for turning R Jupyter Notebooks into Docker images.
Home-page: https://github.com/fracpete/rnb2docker
Author: Peter "fracpete" Reutemann
Author-email: fracpete@gmail.com
License: Apache Software License 2.0
Platform: UNKNOWN
Classifier: Development Status :: 4 - Beta
Classifier: License :: OSI Approved :: Apache Software License
Classifier: Topic :: Scientific/Engineering
Classifier: Programming Language :: Python :: 3
